[{"line":1,"elements":[{"start_timestamp":"2024-10-18T16:02:33.656Z","before":[{"result":{"duration":2175336700,"status":"passed"},"match":{"location":"selenium_mvn_eclipse.LoginSteps.setup()"}}],"line":3,"name":"View cart items and proceed to checkout","description":"","id":"cart-feature;view-cart-items-and-proceed-to-checkout","after":[{"result":{"duration":241807000,"status":"passed"},"match":{"location":"selenium_mvn_eclipse.LoginSteps.teardown()"}}],"type":"scenario","keyword":"Scenario","steps":[{"result":{"duration":6003588500,"status":"passed"},"line":4,"name":"I am logged in to the Sauce Demo site","match":{"location":"selenium_mvn_eclipse.CartSteps.i_am_logged_in_to_the_sauce_demo_site()"},"keyword":"Given "},{"result":{"duration":162089700,"status":"passed"},"line":5,"name":"I click on the cart icon","match":{"location":"selenium_mvn_eclipse.CartSteps.i_click_on_the_cart_icon()"},"keyword":"When "},{"result":{"error_message":"java.lang.AssertionError: Failed to find the cart item on the cart page: Expected condition failed: waiting for visibility of element located by By.className: cart_item (tried for 10 second(s) with 500 milliseconds interval)\nBuild info: version: '4.25.0', revision: '8a8aea2337'\nSystem info: os.name: 'Windows 10', os.arch: 'amd64', os.version: '10.0', java.version: '21.0.3'\nDriver info: org.openqa.selenium.chrome.ChromeDriver\nCapabilities {acceptInsecureCerts: false, browserName: chrome, browserVersion: 130.0.6723.59, chrome: {chromedriverVersion: 130.0.6723.58 (3a50e012e4c9..., userDataDir: C:\\Users\\Grace\\AppData\\Loca...}, fedcm:accounts: true, goog:chromeOptions: {debuggerAddress: localhost:56305}, networkConnectionEnabled: false, pageLoadStrategy: normal, platformName: windows, proxy: Proxy(), se:cdp: ws://localhost:56305/devtoo..., se:cdpVersion: 130.0.6723.59, setWindowRect: true, strictFileInteractability: false, timeouts: {implicit: 0, pageLoad: 300000, script: 30000}, unhandledPromptBehavior: dismiss and notify, webauthn:extension:credBlob: true, webauthn:extension:largeBlob: true, webauthn:extension:minPinLength: true, webauthn:extension:prf: true, webauthn:virtualAuthenticators: true}\nSession ID: 81e36bf73b567123166bf918c8a9b391\r\n\tat org.junit.Assert.fail(Assert.java:89)\r\n\tat selenium_mvn_eclipse.CartSteps.i_should_be_redirected_to_the_cart_page_with_a_cart_item_displayed(CartSteps.java:83)\r\n\tat ✽.I should be redirected to the cart page with a cart item displayed(file:///E:/SQE%20project/selenium_mvn_eclipse/src/test/resources/feature/YourCart.feature:6)\r\n","duration":10393771400,"status":"failed"},"line":6,"name":"I should be redirected to the cart page with a cart item displayed","match":{"location":"selenium_mvn_eclipse.CartSteps.i_should_be_redirected_to_the_cart_page_with_a_cart_item_displayed()"},"keyword":"Then "},{"result":{"duration":764700,"status":"skipped"},"line":7,"name":"I click on the checkout button","match":{"location":"selenium_mvn_eclipse.CartSteps.i_click_on_the_checkout_button()"},"keyword":"When "},{"result":{"status":"skipped"},"line":8,"name":"I should be redirected to the checkout page","match":{"location":"selenium_mvn_eclipse.CartSteps.i_should_be_redirected_to_the_checkout_page()"},"keyword":"Then "}]}],"name":"Cart Feature","description":"","id":"cart-feature","keyword":"Feature","uri":"file:src/test/resources/feature/YourCart.feature","tags":[]},{"line":1,"elements":[{"start_timestamp":"2024-10-18T16:02:52.812Z","before":[{"result":{"duration":1416434200,"status":"passed"},"match":{"location":"selenium_mvn_eclipse.LoginSteps.setup()"}}],"line":12,"name":"Successful Login with valid credentials","description":"","id":"login-feature;successful-login-with-valid-credentials;;2","after":[{"result":{"duration":319186900,"status":"passed"},"match":{"location":"selenium_mvn_eclipse.LoginSteps.teardown()"}}],"type":"scenario","keyword":"Scenario Outline","steps":[{"result":{"duration":3255514100,"status":"passed"},"line":4,"name":"I am on the Sauce Demo login page","match":{"location":"selenium_mvn_eclipse.LoginSteps.i_am_on_the_sauce_demo_login_page()"},"keyword":"Given "},{"result":{"duration":248767600,"status":"passed"},"line":5,"name":"I enter username \"standard_user\"","match":{"arguments":[{"val":"\"standard_user\"","offset":17}],"location":"selenium_mvn_eclipse.LoginSteps.i_enter_username(java.lang.String)"},"keyword":"When "},{"result":{"duration":181911700,"status":"passed"},"line":6,"name":"I enter password \"secret_sauce\"","match":{"arguments":[{"val":"\"secret_sauce\"","offset":17}],"location":"selenium_mvn_eclipse.LoginSteps.i_enter_password(java.lang.String)"},"keyword":"And "},{"result":{"duration":215711000,"status":"passed"},"line":7,"name":"I click on the login button","match":{"location":"selenium_mvn_eclipse.LoginSteps.i_click_on_the_login_button()"},"keyword":"And "},{"result":{"duration":22896700,"status":"passed"},"line":8,"name":"I should be redirected to the Products page with title \"Swag Labs\"","match":{"arguments":[{"val":"\"Swag Labs\"","offset":55}],"location":"selenium_mvn_eclipse.LoginSteps.i_should_be_redirected_to_the_products_page_with_title(java.lang.String)"},"keyword":"Then "}]},{"start_timestamp":"2024-10-18T16:02:58.523Z","before":[{"result":{"duration":1676707000,"status":"passed"},"match":{"location":"selenium_mvn_eclipse.LoginSteps.setup()"}}],"line":13,"name":"Successful Login with valid credentials","description":"","id":"login-feature;successful-login-with-valid-credentials;;3","after":[{"result":{"duration":288791700,"status":"passed"},"match":{"location":"selenium_mvn_eclipse.LoginSteps.teardown()"}}],"type":"scenario","keyword":"Scenario Outline","steps":[{"result":{"duration":3606729800,"status":"passed"},"line":4,"name":"I am on the Sauce Demo login page","match":{"location":"selenium_mvn_eclipse.LoginSteps.i_am_on_the_sauce_demo_login_page()"},"keyword":"Given "},{"result":{"duration":257724500,"status":"passed"},"line":5,"name":"I enter username \"problem_user\"","match":{"arguments":[{"val":"\"problem_user\"","offset":17}],"location":"selenium_mvn_eclipse.LoginSteps.i_enter_username(java.lang.String)"},"keyword":"When "},{"result":{"duration":214735900,"status":"passed"},"line":6,"name":"I enter password \"secret_sauce\"","match":{"arguments":[{"val":"\"secret_sauce\"","offset":17}],"location":"selenium_mvn_eclipse.LoginSteps.i_enter_password(java.lang.String)"},"keyword":"And "},{"result":{"duration":169071100,"status":"passed"},"line":7,"name":"I click on the login button","match":{"location":"selenium_mvn_eclipse.LoginSteps.i_click_on_the_login_button()"},"keyword":"And "},{"result":{"duration":19946600,"status":"passed"},"line":8,"name":"I should be redirected to the Products page with title \"Swag Labs\"","match":{"arguments":[{"val":"\"Swag Labs\"","offset":55}],"location":"selenium_mvn_eclipse.LoginSteps.i_should_be_redirected_to_the_products_page_with_title(java.lang.String)"},"keyword":"Then "}]},{"start_timestamp":"2024-10-18T16:03:04.780Z","before":[{"result":{"duration":1433299700,"status":"passed"},"match":{"location":"selenium_mvn_eclipse.LoginSteps.setup()"}}],"line":14,"name":"Successful Login with valid credentials","description":"","id":"login-feature;successful-login-with-valid-credentials;;4","after":[{"result":{"duration":262963900,"status":"passed"},"match":{"location":"selenium_mvn_eclipse.LoginSteps.teardown()"}}],"type":"scenario","keyword":"Scenario Outline","steps":[{"result":{"duration":3902700700,"status":"passed"},"line":4,"name":"I am on the Sauce Demo login page","match":{"location":"selenium_mvn_eclipse.LoginSteps.i_am_on_the_sauce_demo_login_page()"},"keyword":"Given "},{"result":{"duration":301277900,"status":"passed"},"line":5,"name":"I enter username \"performance_glitch_user\"","match":{"arguments":[{"val":"\"performance_glitch_user\"","offset":17}],"location":"selenium_mvn_eclipse.LoginSteps.i_enter_username(java.lang.String)"},"keyword":"When "},{"result":{"duration":209739600,"status":"passed"},"line":6,"name":"I enter password \"secret_sauce\"","match":{"arguments":[{"val":"\"secret_sauce\"","offset":17}],"location":"selenium_mvn_eclipse.LoginSteps.i_enter_password(java.lang.String)"},"keyword":"And "},{"result":{"duration":5156491300,"status":"passed"},"line":7,"name":"I click on the login button","match":{"location":"selenium_mvn_eclipse.LoginSteps.i_click_on_the_login_button()"},"keyword":"And "},{"result":{"duration":28712200,"status":"passed"},"line":8,"name":"I should be redirected to the Products page with title \"Swag Labs\"","match":{"arguments":[{"val":"\"Swag Labs\"","offset":55}],"location":"selenium_mvn_eclipse.LoginSteps.i_should_be_redirected_to_the_products_page_with_title(java.lang.String)"},"keyword":"Then "}]}],"name":"Login Feature","description":"","id":"login-feature","keyword":"Feature","uri":"file:src/test/resources/feature/login.feature","tags":[]}]